{"type":"FeatureCollection","features":[{"type":"Feature","id":1,"geometry":{"type":"Point","coordinates":[14.261217647000024,57.780819522000058]},"properties":{"ObjectID":1,"Name":"Location 1","TargetFacilityCount":null,"SourceID":1,"SourceOID":81700454,"PosAlong":0.12427025810602092,"SideOfEdge":1,"CurbApproach":0,"Status":7,"SnapX":14.261075320101803,"SnapY":57.780780586363775,"SnapZ":0,"DistanceToNetworkInMeters":9.4946558337495137,"Attr_Minutes":0,"Attr_TimeAt1KPH":0,"Attr_TravelTime":0,"Attr_TruckMinutes":0,"Attr_TruckTravelTime":0,"Attr_WalkTime":0,"Attr_Kilometers":0,"Attr_Miles":0,"Cutoff_Minutes":null,"Cutoff_TimeAt1KPH":null,"Cutoff_TravelTime":null,"Cutoff_TruckMinutes":null,"Cutoff_TruckTravelTime":null,"Cutoff_WalkTime":null,"Cutoff_Kilometers":null,"Cutoff_Miles":null}},{"type":"Feature","id":2,"geometry":{"type":"Point","coordinates":[14.265437834000068,57.777679700000078]},"properties":{"ObjectID":2,"Name":"Location 2","TargetFacilityCount":null,"SourceID":1,"SourceOID":81700838,"PosAlong":0.13167177155445584,"SideOfEdge":1,"CurbApproach":0,"Status":7,"SnapX":14.265404949187328,"SnapY":57.777595765430419,"SnapZ":0,"DistanceToNetworkInMeters":9.5454183397957504,"Attr_Minutes":0,"Attr_TimeAt1KPH":0,"Attr_TravelTime":0,"Attr_TruckMinutes":0,"Attr_TruckTravelTime":0,"Attr_WalkTime":0,"Attr_Kilometers":0,"Attr_Miles":0,"Cutoff_Minutes":null,"Cutoff_TimeAt1KPH":null,"Cutoff_TravelTime":null,"Cutoff_TruckMinutes":null,"Cutoff_TruckTravelTime":null,"Cutoff_WalkTime":null,"Cutoff_Kilometers":null,"Cutoff_Miles":null}},{"type":"Feature","id":3,"geometry":{"type":"Point","coordinates":[14.25903975500006,57.775299797000059]},"properties":{"ObjectID":3,"Name":"Location 3","TargetFacilityCount":null,"SourceID":1,"SourceOID":81700401,"PosAlong":0.095615647850278596,"SideOfEdge":1,"CurbApproach":0,"Status":0,"SnapX":14.259034888026633,"SnapY":57.775434365827437,"SnapZ":0,"DistanceToNetworkInMeters":14.982856798889118,"Attr_Minutes":0,"Attr_TimeAt1KPH":0,"Attr_TravelTime":0,"Attr_TruckMinutes":0,"Attr_TruckTravelTime":0,"Attr_WalkTime":0,"Attr_Kilometers":0,"Attr_Miles":0,"Cutoff_Minutes":null,"Cutoff_TimeAt1KPH":null,"Cutoff_TravelTime":null,"Cutoff_TruckMinutes":null,"Cutoff_TruckTravelTime":null,"Cutoff_WalkTime":null,"Cutoff_Kilometers":null,"Cutoff_Miles":null}},{"type":"Feature","id":4,"geometry":{"type":"Point","coordinates":[14.267545296000037,57.772184882000033]},"properties":{"ObjectID":4,"Name":"Location 4","TargetFacilityCount":null,"SourceID":1,"SourceOID":81700719,"PosAlong":0.91640545550921315,"SideOfEdge":2,"CurbApproach":0,"Status":7,"SnapX":14.267893300000026,"SnapY":57.771609100000035,"SnapZ":0,"DistanceToNetworkInMeters":67.343026774371538,"Attr_Minutes":0,"Attr_TimeAt1KPH":0,"Attr_TravelTime":0,"Attr_TruckMinutes":0,"Attr_TruckTravelTime":0,"Attr_WalkTime":0,"Attr_Kilometers":0,"Attr_Miles":0,"Cutoff_Minutes":null,"Cutoff_TimeAt1KPH":null,"Cutoff_TravelTime":null,"Cutoff_TruckMinutes":null,"Cutoff_TruckTravelTime":null,"Cutoff_WalkTime":null,"Cutoff_Kilometers":null,"Cutoff_Miles":null}}]}