{"type":"FeatureCollection","features":[{"type":"Feature","id":1,"geometry":{"type":"Point","coordinates":[14.264752861000034,57.779179230000068]},"properties":{"ObjectID":1,"Name":"Location 1","TargetFacilityCount":null,"SourceID":1,"SourceOID":81700387,"PosAlong":0.98680928184251948,"SideOfEdge":2,"CurbApproach":0,"Status":0,"SnapX":14.264751877177135,"SnapY":57.779160894286782,"SnapZ":0,"DistanceToNetworkInMeters":2.0428427799488107,"Attr_Minutes":0,"Attr_TimeAt1KPH":0,"Attr_TravelTime":0,"Attr_TruckMinutes":0,"Attr_TruckTravelTime":0,"Attr_WalkTime":0,"Attr_Kilometers":0,"Attr_Miles":0,"Cutoff_Minutes":null,"Cutoff_TimeAt1KPH":null,"Cutoff_TravelTime":null,"Cutoff_TruckMinutes":null,"Cutoff_TruckTravelTime":null,"Cutoff_WalkTime":null,"Cutoff_Kilometers":null,"Cutoff_Miles":null}},{"type":"Feature","id":2,"geometry":{"type":"Point","coordinates":[14.259955527000045,57.775322630000062]},"properties":{"ObjectID":2,"Name":"Location 2","TargetFacilityCount":null,"SourceID":1,"SourceOID":81700401,"PosAlong":0.36931758558741862,"SideOfEdge":1,"CurbApproach":0,"Status":0,"SnapX":14.2599502884292,"SnapY":57.775467473267859,"SnapZ":0,"DistanceToNetworkInMeters":16.126862126544179,"Attr_Minutes":0,"Attr_TimeAt1KPH":0,"Attr_TravelTime":0,"Attr_TruckMinutes":0,"Attr_TruckTravelTime":0,"Attr_WalkTime":0,"Attr_Kilometers":0,"Attr_Miles":0,"Cutoff_Minutes":null,"Cutoff_TimeAt1KPH":null,"Cutoff_TravelTime":null,"Cutoff_TruckMinutes":null,"Cutoff_TruckTravelTime":null,"Cutoff_WalkTime":null,"Cutoff_Kilometers":null,"Cutoff_Miles":null}},{"type":"Feature","id":3,"geometry":{"type":"Point","coordinates":[14.267657411000073,57.773112106000042]},"properties":{"ObjectID":3,"Name":"Location 3","TargetFacilityCount":null,"SourceID":1,"SourceOID":81700652,"PosAlong":0.59112220067182608,"SideOfEdge":2,"CurbApproach":0,"Status":0,"SnapX":14.267661629474091,"SnapY":57.773123707693571,"SnapZ":0,"DistanceToNetworkInMeters":1.3169356991809553,"Attr_Minutes":0,"Attr_TimeAt1KPH":0,"Attr_TravelTime":0,"Attr_TruckMinutes":0,"Attr_TruckTravelTime":0,"Attr_WalkTime":0,"Attr_Kilometers":0,"Attr_Miles":0,"Cutoff_Minutes":null,"Cutoff_TimeAt1KPH":null,"Cutoff_TravelTime":null,"Cutoff_TruckMinutes":null,"Cutoff_TruckTravelTime":null,"Cutoff_WalkTime":null,"Cutoff_Kilometers":null,"Cutoff_Miles":null}},{"type":"Feature","id":4,"geometry":{"type":"Point","coordinates":[14.260303879000048,57.780691816000058]},"properties":{"ObjectID":4,"Name":"Location 4","TargetFacilityCount":null,"SourceID":1,"SourceOID":81700457,"PosAlong":0.82707198437365637,"SideOfEdge":2,"CurbApproach":0,"Status":0,"SnapX":14.260307343303154,"SnapY":57.780635560009046,"SnapZ":0,"DistanceToNetworkInMeters":6.2655444766598087,"Attr_Minutes":0,"Attr_TimeAt1KPH":0,"Attr_TravelTime":0,"Attr_TruckMinutes":0,"Attr_TruckTravelTime":0,"Attr_WalkTime":0,"Attr_Kilometers":0,"Attr_Miles":0,"Cutoff_Minutes":null,"Cutoff_TimeAt1KPH":null,"Cutoff_TravelTime":null,"Cutoff_TruckMinutes":null,"Cutoff_TruckTravelTime":null,"Cutoff_WalkTime":null,"Cutoff_Kilometers":null,"Cutoff_Miles":null}}]}