{"type":"FeatureCollection","features":[{"type":"Feature","id":1,"geometry":{"type":"Point","coordinates":[14.268995272000041,57.772484992000045]},"properties":{"ObjectID":1,"Name":"Location 1","TargetFacilityCount":null,"SourceID":1,"SourceOID":81700652,"PosAlong":0.14815379166828341,"SideOfEdge":1,"CurbApproach":0,"Status":0,"SnapX":14.268919525662874,"SnapY":57.772444894441342,"SnapZ":0,"DistanceToNetworkInMeters":6.3350801353779786,"Attr_Minutes":0,"Attr_TimeAt1KPH":0,"Attr_TravelTime":0,"Attr_TruckMinutes":0,"Attr_TruckTravelTime":0,"Attr_WalkTime":0,"Attr_Kilometers":0,"Attr_Miles":0,"Cutoff_Minutes":null,"Cutoff_TimeAt1KPH":null,"Cutoff_TravelTime":null,"Cutoff_TruckMinutes":null,"Cutoff_TruckTravelTime":null,"Cutoff_WalkTime":null,"Cutoff_Kilometers":null,"Cutoff_Miles":null}},{"type":"Feature","id":2,"geometry":{"type":"Point","coordinates":[14.258098616000041,57.77531723900006]},"properties":{"ObjectID":2,"Name":"Location 2","TargetFacilityCount":null,"SourceID":1,"SourceOID":81700333,"PosAlong":0.051419229394628292,"SideOfEdge":2,"CurbApproach":0,"Status":0,"SnapX":14.258095611699279,"SnapY":57.775400349572415,"SnapZ":0,"DistanceToNetworkInMeters":9.2537577241094624,"Attr_Minutes":0,"Attr_TimeAt1KPH":0,"Attr_TravelTime":0,"Attr_TruckMinutes":0,"Attr_TruckTravelTime":0,"Attr_WalkTime":0,"Attr_Kilometers":0,"Attr_Miles":0,"Cutoff_Minutes":null,"Cutoff_TimeAt1KPH":null,"Cutoff_TravelTime":null,"Cutoff_TruckMinutes":null,"Cutoff_TruckTravelTime":null,"Cutoff_WalkTime":null,"Cutoff_Kilometers":null,"Cutoff_Miles":null}},{"type":"Feature","id":3,"geometry":{"type":"Point","coordinates":[14.259319909000055,57.78059647300006]},"properties":{"ObjectID":3,"Name":"Location 3","TargetFacilityCount":null,"SourceID":1,"SourceOID":81700457,"PosAlong":0.45951661586774106,"SideOfEdge":2,"CurbApproach":0,"Status":0,"SnapX":14.259321241501775,"SnapY":57.780574834822758,"SnapZ":0,"DistanceToNetworkInMeters":2.4118866291079093,"Attr_Minutes":0,"Attr_TimeAt1KPH":0,"Attr_TravelTime":0,"Attr_TruckMinutes":0,"Attr_TruckTravelTime":0,"Attr_WalkTime":0,"Attr_Kilometers":0,"Attr_Miles":0,"Cutoff_Minutes":null,"Cutoff_TimeAt1KPH":null,"Cutoff_TravelTime":null,"Cutoff_TruckMinutes":null,"Cutoff_TruckTravelTime":null,"Cutoff_WalkTime":null,"Cutoff_Kilometers":null,"Cutoff_Miles":null}},{"type":"Feature","id":4,"geometry":{"type":"Point","coordinates":[14.265741202000072,57.779158735000067]},"properties":{"ObjectID":4,"Name":"Location 4","TargetFacilityCount":null,"SourceID":1,"SourceOID":81700809,"PosAlong":0.18718103835427033,"SideOfEdge":1,"CurbApproach":0,"Status":0,"SnapX":14.265738475894702,"SnapY":57.77910794266063,"SnapZ":0,"DistanceToNetworkInMeters":5.6563755280377235,"Attr_Minutes":0,"Attr_TimeAt1KPH":0,"Attr_TravelTime":0,"Attr_TruckMinutes":0,"Attr_TruckTravelTime":0,"Attr_WalkTime":0,"Attr_Kilometers":0,"Attr_Miles":0,"Cutoff_Minutes":null,"Cutoff_TimeAt1KPH":null,"Cutoff_TravelTime":null,"Cutoff_TruckMinutes":null,"Cutoff_TruckTravelTime":null,"Cutoff_WalkTime":null,"Cutoff_Kilometers":null,"Cutoff_Miles":null}},{"type":"Feature","id":5,"geometry":{"type":"Point","coordinates":[14.266548004000072,57.777196616000083]},"properties":{"ObjectID":5,"Name":"Location 5","TargetFacilityCount":null,"SourceID":1,"SourceOID":81700807,"PosAlong":0.76242764661528672,"SideOfEdge":1,"CurbApproach":0,"Status":0,"SnapX":14.266546925759311,"SnapY":57.777187229922411,"SnapZ":0,"DistanceToNetworkInMeters":1.0454581230878841,"Attr_Minutes":0,"Attr_TimeAt1KPH":0,"Attr_TravelTime":0,"Attr_TruckMinutes":0,"Attr_TruckTravelTime":0,"Attr_WalkTime":0,"Attr_Kilometers":0,"Attr_Miles":0,"Cutoff_Minutes":null,"Cutoff_TimeAt1KPH":null,"Cutoff_TravelTime":null,"Cutoff_TruckMinutes":null,"Cutoff_TruckTravelTime":null,"Cutoff_WalkTime":null,"Cutoff_Kilometers":null,"Cutoff_Miles":null}}]}